{
  "last_updated": "2026-06-12 14:39 UTC",
  "standings": [
    {
      "person": "Rice",
      "teams": [
        {
          "team": "Yankees",
          "wins": 41,
          "losses": 26
        },
        {
          "team": "Brewers",
          "wins": 41,
          "losses": 25
        },
        {
          "team": "Astros",
          "wins": 31,
          "losses": 39
        },
        {
          "team": "Rays",
          "wins": 40,
          "losses": 25
        },
        {
          "team": "Nationals",
          "wins": 35,
          "losses": 34
        }
      ],
      "total_wins": 188,
      "total_losses": 149,
      "win_pct": ".558",
      "rank": 1
    },
    {
      "person": "Tim",
      "teams": [
        {
          "team": "Phillies",
          "wins": 37,
          "losses": 31
        },
        {
          "team": "Blue Jays",
          "wins": 33,
          "losses": 36
        },
        {
          "team": "D-backs",
          "wins": 34,
          "losses": 34
        },
        {
          "team": "Pirates",
          "wins": 35,
          "losses": 34
        },
        {
          "team": "Cardinals",
          "wins": 37,
          "losses": 29
        }
      ],
      "total_wins": 176,
      "total_losses": 164,
      "win_pct": ".518",
      "rank": 2
    },
    {
      "person": "Hudson",
      "teams": [
        {
          "team": "Dodgers",
          "wins": 44,
          "losses": 25
        },
        {
          "team": "Padres",
          "wins": 35,
          "losses": 32
        },
        {
          "team": "Guardians",
          "wins": 37,
          "losses": 33
        },
        {
          "team": "Twins",
          "wins": 31,
          "losses": 39
        },
        {
          "team": "Angels",
          "wins": 27,
          "losses": 42
        }
      ],
      "total_wins": 174,
      "total_losses": 171,
      "win_pct": ".504",
      "rank": 3
    },
    {
      "person": "Perry",
      "teams": [
        {
          "team": "Mariners",
          "wins": 36,
          "losses": 34
        },
        {
          "team": "Tigers",
          "wins": 29,
          "losses": 40
        },
        {
          "team": "Orioles",
          "wins": 33,
          "losses": 37
        },
        {
          "team": "Athletics",
          "wins": 33,
          "losses": 35
        },
        {
          "team": "White Sox",
          "wins": 36,
          "losses": 31
        }
      ],
      "total_wins": 167,
      "total_losses": 177,
      "win_pct": ".485",
      "rank": 4
    },
    {
      "person": "Brian",
      "teams": [
        {
          "team": "Cubs",
          "wins": 35,
          "losses": 34
        },
        {
          "team": "Red Sox",
          "wins": 27,
          "losses": 39
        },
        {
          "team": "Rangers",
          "wins": 34,
          "losses": 34
        },
        {
          "team": "Reds",
          "wins": 32,
          "losses": 35
        },
        {
          "team": "Marlins",
          "wins": 34,
          "losses": 35
        }
      ],
      "total_wins": 162,
      "total_losses": 177,
      "win_pct": ".478",
      "rank": 5
    },
    {
      "person": "Porter",
      "teams": [
        {
          "team": "Braves",
          "wins": 45,
          "losses": 23
        },
        {
          "team": "Mets",
          "wins": 30,
          "losses": 38
        },
        {
          "team": "Royals",
          "wins": 28,
          "losses": 41
        },
        {
          "team": "Giants",
          "wins": 28,
          "losses": 41
        },
        {
          "team": "Rockies",
          "wins": 26,
          "losses": 43
        }
      ],
      "total_wins": 157,
      "total_losses": 186,
      "win_pct": ".458",
      "rank": 6
    }
  ]
}